{
 "version": "5.0.1",
 "flags": {},
 "imagePath": "090.jpg",
 "imageData": null,
 "imageHeight": 1280,
 "imageWidth": 720,
 "shapes": [
  {
   "label": "person",
   "points": [
    [
     247,
     522
    ],
    [
     456,
     994
    ]
   ],
   "shape_type": "rectangle",
   "flags": {}
  },
  {
   "label": "person",
   "points": [
    [
     440,
     506
    ],
    [
     595,
     841
    ]
   ],
   "shape_type": "rectangle",
   "flags": {}
  },
  {
   "label": "person",
   "points": [
    [
     418,
     504
    ],
    [
     442,
     565
    ]
   ],
   "shape_type": "rectangle",
   "flags": {}
  },
  {
   "label": "person",
   "points": [
    [
     397,
     493
    ],
    [
     413,
     539
    ]
   ],
   "shape_type": "rectangle",
   "flags": {}
  },
  {
   "label": "person",
   "points": [
    [
     368,
     493
    ],
    [
     384,
     545
    ]
   ],
   "shape_type": "rectangle",
   "flags": {}
  },
  {
   "label": "person",
   "points": [
    [
     350,
     494
    ],
    [
     365,
     541
    ]
   ],
   "shape_type": "rectangle",
   "flags": {}
  },
  {
   "label": "person",
   "points": [
    [
     376,
     494
    ],
    [
     394,
     546
    ]
   ],
   "shape_type": "rectangle",
   "flags": {}
  },
  {
   "label": "person",
   "points": [
    [
     452,
     492
    ],
    [
     470,
     551
    ]
   ],
   "shape_type": "rectangle",
   "flags": {}
  },
  {
   "label": "person",
   "points": [
    [
     447,
     492
    ],
    [
     471,
     571
    ]
   ],
   "shape_type": "rectangle",
   "flags": {}
  },
  {
   "label": "motorcycle",
   "points": [
    [
     1,
     632
    ],
    [
     97,
     748
    ]
   ],
   "shape_type": "rectangle",
   "flags": {}
  },
  {
   "label": "motorcycle",
   "points": [
    [
     35,
     587
    ],
    [
     144,
     711
    ]
   ],
   "shape_type": "rectangle",
   "flags": {}
  },
  {
   "label": "motorcycle",
   "points": [
    [
     160,
     571
    ],
    [
     230,
     661
    ]
   ],
   "shape_type": "rectangle",
   "flags": {}
  },
  {
   "label": "motorcycle",
   "points": [
    [
     106,
     578
    ],
    [
     185,
     688
    ]
   ],
   "shape_type": "rectangle",
   "flags": {}
  },
  {
   "label": "motorcycle",
   "points": [
    [
     211,
     544
    ],
    [
     288,
     624
    ]
   ],
   "shape_type": "rectangle",
   "flags": {}
  },
  {
   "label": "handbag",
   "points": [
    [
     442,
     575
    ],
    [
     530,
     702
    ]
   ],
   "shape_type": "rectangle",
   "flags": {}
  },
  {
   "label": "handbag",
   "points": [
    [
     441,
     590
    ],
    [
     502,
     695
    ]
   ],
   "shape_type": "rectangle",
   "flags": {}
  }
 ]
}