{
 "version": "5.0.1",
 "flags": {},
 "imagePath": "055.jpg",
 "imageData": null,
 "imageHeight": 1280,
 "imageWidth": 720,
 "shapes": [
  {
   "label": "person",
   "points": [
    [
     44,
     415
    ],
    [
     133,
     627
    ]
   ],
   "shape_type": "rectangle",
   "flags": {}
  },
  {
   "label": "person",
   "points": [
    [
     448,
     421
    ],
    [
     522,
     620
    ]
   ],
   "shape_type": "rectangle",
   "flags": {}
  },
  {
   "label": "motorcycle",
   "points": [
    [
     308,
     457
    ],
    [
     449,
     571
    ]
   ],
   "shape_type": "rectangle",
   "flags": {}
  },
  {
   "label": "motorcycle",
   "points": [
    [
     520,
     445
    ],
    [
     608,
     569
    ]
   ],
   "shape_type": "rectangle",
   "flags": {}
  },
  {
   "label": "motorcycle",
   "points": [
    [
     608,
     459
    ],
    [
     713,
     562
    ]
   ],
   "shape_type": "rectangle",
   "flags": {}
  },
  {
   "label": "motorcycle",
   "points": [
    [
     156,
     460
    ],
    [
     251,
     544
    ]
   ],
   "shape_type": "rectangle",
   "flags": {}
  },
  {
   "label": "motorcycle",
   "points": [
    [
     113,
     457
    ],
    [
     250,
     546
    ]
   ],
   "shape_type": "rectangle",
   "flags": {}
  },
  {
   "label": "motorcycle",
   "points": [
    [
     654,
     464
    ],
    [
     717,
     572
    ]
   ],
   "shape_type": "rectangle",
   "flags": {}
  }
 ]
}